bcca/__init__.py
bcca/pytest_plugin.py
bcca/test.py
bcca/what_have_i_done.py
bcca-1.7.0.dist-info/LICENSE
bcca-1.7.0.dist-info/METADATA
bcca-1.7.0.dist-info/WHEEL
bcca-1.7.0.dist-info/entry_points.txt
bcca-1.7.0.dist-info/top_level.txt
bcca-1.7.0.dist-info/RECORD
