Metadata-Version: 2.1
Name: bcca
Version: 1.7.0
Summary: Helpers from Base Camp Coding Academy
Home-page: UNKNOWN
Author: UNKNOWN
Author-email: UNKNOWN
License: UNKNOWN
Platform: UNKNOWN
Requires-Dist: pytest
Requires-Dist: click
Requires-Dist: colorama
